CHANGES.txt
LICENSE.GPL
LICENSE.txt
README.txt
bootstrap.py
buildout.cfg
setup.py
collective/__init__.py
collective.cicero.egg-info/PKG-INFO
collective.cicero.egg-info/SOURCES.txt
collective.cicero.egg-info/dependency_links.txt
collective.cicero.egg-info/namespace_packages.txt
collective.cicero.egg-info/not-zip-safe
collective.cicero.egg-info/requires.txt
collective.cicero.egg-info/top_level.txt
collective/cicero/__init__.py
collective/cicero/browser.py
collective/cicero/config.py
collective/cicero/configure.zcml
collective/cicero/interfaces.py
collective/cicero/profiles/default/controlpanel.xml
collective/cicero/profiles/default/metadata.xml
collective/cicero/profiles/default/registry.xml
collective/cicero/tests/ElectedOfficialQueryService.wsdl
collective/cicero/tests/ElectedOfficialQueryService_GetOfficialsByAddress.txt
collective/cicero/tests/__init__.py
collective/cicero/tests/tests.py