Metadata-Version: 1.0
Name: collective.cicero
Version: 1.1
Summary: Provides access to Azavea's Cicero API for legistrative district matching and elected official info
Home-page: http://svn.plone.org/svn/collective/collective.cicero/trunk
Author: David Glick, Groundwire
Author-email: davidglick@groundwire.org
License: GPL
Keywords: azavea cicero legislative lookup elected official soap zope plone
Platform: UNKNOWN
Classifier: Programming Language :: Python
